README.md
setup.py
level3_NI_test/Level1.py
level3_NI_test/Level2.py
level3_NI_test/__init__.py
level3_NI_test/level1.py
level3_NI_test/level2.py
level3_NI_test/level3.py
level3_NI_test.egg-info/PKG-INFO
level3_NI_test.egg-info/SOURCES.txt
level3_NI_test.egg-info/dependency_links.txt
level3_NI_test.egg-info/top_level.txt