Metadata-Version: 2.1
Name: level3-NI-test
Version: 0.2.1
Summary: Test uploading module to PyPi
Author: Hamza Daoud
Author-email: hamzadaoud99@gmail.com
Classifier: Development Status :: 3 - Alpha
Classifier: Intended Audience :: Developers
Classifier: License :: OSI Approved :: MIT License
Classifier: Programming Language :: Python :: 3
Classifier: Programming Language :: Python :: 3.6
Classifier: Programming Language :: Python :: 3.7
Classifier: Programming Language :: Python :: 3.8
